{"0": "affirm", "1": "agradece", "2": "ano1-livro", "3": "ano1-materia", "4": "ano2-livro", "5": "ano2-materia", "6": "ano3-livro", "7": "ano3-materia", "8": "ano4-livro", "9": "ano4-materia", "10": "ano5-livro", "11": "ano5-materia", "12": "aovivo", "13": "att", "14": "baja", "15": "ca", "16": "deny", "17": "dina", "18": "duvida", "19": "duvida2", "20": "duvida3", "21": "enactus", "22": "gaia", "23": "gera", "24": "goodbye", "25": "greet", "26": "optativa-materia", "27": "pet", "28": "rede", "29": "sme", "30": "tromba"}